sophia2/__init__.py
sophia2/db.py
sophia2/sophia2.py
sophia2-0.0.0.1.dist-info/LICENSE
sophia2-0.0.0.1.dist-info/METADATA
sophia2-0.0.0.1.dist-info/WHEEL
sophia2-0.0.0.1.dist-info/top_level.txt
sophia2-0.0.0.1.dist-info/RECORD
