Metadata-Version: 2.1
Name: sophia2
Version: 0.0.0.1
Summary: Python library for news dircourse analysis
Home-page: https://sophia2.readthedocs.io/en/latest/
Author: Team Sophia2
Author-email: sophia2.uach@gmail.com
License: MIT
Platform: UNKNOWN
Classifier: Programming Language :: Python :: 3
Classifier: Programming Language :: Python :: 3.7
Requires-Dist: pandas
